YOLODetectionAugment/AugmentHelper.py
YOLODetectionAugment/ToTxt.py
YOLODetectionAugment/ToXml.py
YOLODetectionAugment/__init__.py
YOLODetectionAugment/enlarge.py
YOLODetectionAugment/spltdata.py
yolodetectionaugment-0.0.1.dist-info/LICENSE
yolodetectionaugment-0.0.1.dist-info/METADATA
yolodetectionaugment-0.0.1.dist-info/WHEEL
yolodetectionaugment-0.0.1.dist-info/top_level.txt
yolodetectionaugment-0.0.1.dist-info/RECORD
