Metadata-Version: 2.2
Name: YOLODetectionAugment
Version: 0.0.1
Summary: A data augmentation package for converting segmentation data to detection data.
Home-page: https://github.com/Huuuuugh/YOLODetectionAugment
Author: XavierHugh
Author-email: 2396392765@qq.com
Classifier: Programming Language :: Python :: 3
Classifier: License :: OSI Approved :: MIT License
Classifier: Operating System :: OS Independent
Requires-Python: >=3.6
License-File: LICENSE
Requires-Dist: opencv-python
Requires-Dist: tqdm
Requires-Dist: numpy
Requires-Dist: scikit-image
Requires-Dist: lxml
Dynamic: author
Dynamic: author-email
Dynamic: classifier
Dynamic: description
Dynamic: description-content-type
Dynamic: home-page
Dynamic: requires-dist
Dynamic: requires-python
Dynamic: summary
